networkz/VERSION
networkz/__init__.py
networkz/algorithms/__init__.py
networkz/algorithms/approximation/__init__.py
networkz/algorithms/approximation/coalition_formation.py
networkz/algorithms/approximation/tests/__init__.py
networkz/algorithms/approximation/tests/test_coalition_formation.py
networkz/algorithms/bipartite/__init__.py
networkz/algorithms/bipartite/rank_maximal_matching.py
networkz/algorithms/bipartite/tests/__init__.py
networkz/algorithms/bipartite/tests/test_rank_maximal_matching.py
networkz/classes/__init__.py
networkz/drawing/__init__.py
networkz/generators/__init__.py
networkz/linalg/__init__.py
networkz/readwrite/__init__.py
networkz/tests/__init__.py
networkz/tests/test_example.py
networkz/utils/__init__.py
networkz-1.0.5.dist-info/LICENSE
networkz-1.0.5.dist-info/METADATA
networkz-1.0.5.dist-info/WHEEL
networkz-1.0.5.dist-info/top_level.txt
networkz-1.0.5.dist-info/RECORD
