Metadata-Version: 2.1
Name: networkz
Version: 1.0.5
Summary: NetworkX plus plus
Home-page: https://github.com/ariel-research/networkz
Author: Ariel University
Author-email: networkz@csariel.xyz
License: MIT
Project-URL: Bug Reports, https://github.com/ariel-research/networkz/issues
Project-URL: Source Code, https://github.com/ariel-research/networkz
Keywords: optimization,graphs
Classifier: Development Status :: 2 - Pre-Alpha
Requires-Python: >=3.8
License-File: LICENSE
Requires-Dist: networkx
